main.py
aapt_mcp_server-1.0.0.dist-info/METADATA
aapt_mcp_server-1.0.0.dist-info/WHEEL
aapt_mcp_server-1.0.0.dist-info/entry_points.txt
aapt_mcp_server-1.0.0.dist-info/top_level.txt
aapt_mcp_server-1.0.0.dist-info/RECORD
