Metadata-Version: 2.4
Name: aapt-mcp-server
Version: 1.0.0
Summary: An MCP server that provides APK analysis capabilities using the Android Asset Packaging Tool (aapt)
Requires-Python: >=3.12
Requires-Dist: mcp>=1.9.0
